numcodecs_wasm_tthresh/__init__.py
numcodecs_wasm_tthresh/__init__.pyi
numcodecs_wasm_tthresh/codec.wasm
numcodecs_wasm_tthresh/py.typed
numcodecs_wasm_tthresh-0.3.0.dist-info/METADATA
numcodecs_wasm_tthresh-0.3.0.dist-info/WHEEL
numcodecs_wasm_tthresh-0.3.0.dist-info/entry_points.txt
numcodecs_wasm_tthresh-0.3.0.dist-info/top_level.txt
numcodecs_wasm_tthresh-0.3.0.dist-info/RECORD
